dummy/__init__.py
dummy/dummy.py
dummy/util.py
dummy_test_derek-0.0.0.dist-info/LICENSE
dummy_test_derek-0.0.0.dist-info/METADATA
dummy_test_derek-0.0.0.dist-info/WHEEL
dummy_test_derek-0.0.0.dist-info/top_level.txt
dummy_test_derek-0.0.0.dist-info/RECORD
